multicloud_data_catalogue/main.py
multicloud_data_catalogue/providers/aws.py
multicloud_data_catalogue/providers/aws_storage/dynamo.py
multicloud_data_catalogue/providers/aws_storage/rds.py
multicloud_data_catalogue-0.1.0.dist-info/LICENSE
multicloud_data_catalogue-0.1.0.dist-info/METADATA
multicloud_data_catalogue-0.1.0.dist-info/WHEEL
multicloud_data_catalogue-0.1.0.dist-info/entry_points.txt
multicloud_data_catalogue-0.1.0.dist-info/RECORD
